DESCRIPTION
MANIFEST.in
setup.cfg
setup.py
LinOtpUserIdResolver.egg-info/PKG-INFO
LinOtpUserIdResolver.egg-info/SOURCES.txt
LinOtpUserIdResolver.egg-info/dependency_links.txt
LinOtpUserIdResolver.egg-info/requires.txt
LinOtpUserIdResolver.egg-info/top_level.txt
test/test_resolve.py
test/test_resolve_ldap.py
test/test_resolve_pwd.py
useridresolver/HTTPIdResolver.py
useridresolver/LDAPIdResolver.py
useridresolver/PasswdIdResolver.py
useridresolver/SCIMIdResolver.py
useridresolver/SQLIdResolver.py
useridresolver/UserIdResolver.py
useridresolver/__init__.py