Metadata-Version: 1.1
Name: LinOtpUserIdResolver
Version: 2.9.1.4
Summary: LinOTP2 modules for resolving usernames
Home-page: https://www.linotp.org
Author: KeyIdentity GmbH
Author-email: linotp@keyidentity.com
License: AGPLv3, (C) KeyIdentity GmbH
Keywords: OTP LinOTP2 Login UserId LDAP SQL
Platform: UNKNOWN
Classifier: Framework :: Pylons
Classifier: License :: OSI Approved :: GNU Affero General Public License v3
Classifier: Programming Language :: Python
Classifier: Topic :: Internet
Classifier: Topic :: Security
Classifier: Topic :: System :: Systems Administration :: Authentication/Directory
